DESCRIPTION.rst
MANIFEST.in
README.rst
setup.cfg
setup.py
synoacl/__init__.py
synoacl/tool.py
synoacl.egg-info/PKG-INFO
synoacl.egg-info/SOURCES.txt
synoacl.egg-info/dependency_links.txt
synoacl.egg-info/top_level.txt
tests/__init__.py
tests/test_tool.py